[
  {
    "date": "2026-04-04",
    "post_type": "daily_forecast",
    "content": "4/4(土)東京ディズニーランド攻略プラン🎢\n曇り予報で19個制覇可能！\n総待ち408分の超高効率ルート✨\n\n朝イチはカリブの海賊→ジャングルクルーズがベスト🎯\n\n9:00〜21:00の全プランはリプ欄👇\n\n#東京ディズニーランド\n\n※過去データに基づくシミュレーションです",
    "status": "posted",
    "posted_at": "2026-04-04T22:00:46.595396+00:00",
    "impressions": 0,
    "engagements": 0
  },
  {
    "date": "2026-04-04",
    "post_type": "weekend_forecast",
    "content": "📅 今週末の東京ディズニーシー混雑予測\n\n🔵 土曜 4/4: Lv.3(やや混雑)\n🔵 日曜 4/5: Lv.3(やや混雑)\n\n天気: 晴れ\nおすすめ: 土曜がやや空いてます\n\n※過去データに基づくシミュレーションです",
    "status": "posted",
    "posted_at": "2026-04-02T11:00:08.356194+00:00",
    "impressions": 0,
    "engagements": 0
  },
  {
    "date": "2026-04-04",
    "post_type": "weekend_forecast",
    "content": "📅 今週末の東京ディズニーランド混雑予測\n\n🔵 土曜 4/4: Lv.2(普通)\n🔵 日曜 4/5: Lv.2(普通)\n\n天気: 晴れ\nおすすめ: 土曜がやや空いてます\n\n※過去データに基づくシミュレーションです",
    "status": "posted",
    "posted_at": "2026-04-02T11:00:05.725986+00:00",
    "impressions": 0,
    "engagements": 0
  },
  {
    "date": "2026-04-03",
    "post_type": "answer_check",
    "content": "📋4/3 東京ディズニーシー 振り返り\n\n実現率:70%(7/10個)\n予定609分→実際724分\n⬆️タワテラ:予105→実147\n✅マジックランプシアター:予25→実25\n\n※過去データに基づくシミュレーションです",
    "status": "posted",
    "posted_at": "2026-04-04T03:00:03.648000+00:00",
    "impressions": 0,
    "engagements": 0
  },
  {
    "date": "2026-04-03",
    "post_type": "answer_check",
    "content": "📋4/3 東京ディズニーランド 振り返り\n\n実現率:45%(5/11個)\n予定607分→実際822分\n⬆️ビッグサンダー:予46→実117\n✅美女と野獣:予98→実118\n\n※過去データに基づくシミュレーションです",
    "status": "posted",
    "posted_at": "2026-04-04T03:00:02.507990+00:00",
    "impressions": 0,
    "engagements": 0
  },
  {
    "date": "2026-04-03",
    "post_type": "daily_forecast",
    "content": "【雨の日TDS攻略】東京ディズニーシーで10個制覇🌧️\n待ち480分・移動42分の効率プラン！\n朝イチはトイマニ→タワテラ→タートル・トークが最強✨\n最高効率ルートはリプ欄👇\n※過去データに基づくシミュレーションです\n#東京ディズニーシー",
    "status": "posted",
    "posted_at": "2026-04-03T22:01:18.023639+00:00",
    "impressions": 0,
    "engagements": 0
  },
  {
    "date": "2026-04-03",
    "post_type": "daily_forecast",
    "content": "【雨の日攻略】4/3東京ディズニーランド☔\nなんと11個制覇！総待ち505分\n朝イチは美女と野獣→モンイン→ベイマックス🎢\n雨の日こそ狙い目の効率プラン！\n最高効率ルートはリプ欄👇\n#東京ディズニーランド\n※過去データに基づくシミュレーションです",
    "status": "posted",
    "posted_at": "2026-04-03T22:00:42.275206+00:00",
    "impressions": 0,
    "engagements": 0
  },
  {
    "date": "2026-04-02",
    "post_type": "answer_check",
    "content": "📋4/2 東京ディズニーシー 振り返り\n\n実現率:100%(13/13個)\n予定601分→実際576分\n⬆️センター:予146→実112\n✅アクアトピア:予5→実5\n\n※過去データに基づくシミュレーションです",
    "status": "posted",
    "posted_at": "2026-04-03T03:00:02.964093+00:00",
    "impressions": 0,
    "engagements": 0
  },
  {
    "date": "2026-04-02",
    "post_type": "answer_check",
    "content": "📋4/2 東京ディズニーランド 振り返り\n\n実現率:95%(18/19個)\n予定609分→実際614分\n⬆️カヌー:予26→実5\n✅カリブの海賊:予11→実11\n\n※過去データに基づくシミュレーションです",
    "status": "posted",
    "posted_at": "2026-04-03T03:00:01.884517+00:00",
    "impressions": 0,
    "engagements": 0
  },
  {
    "date": "2026-04-02",
    "post_type": "daily_forecast",
    "content": "【東京ディズニーシー攻略】4/2曇り\nアトラクション13個制覇可能🎭総待ち492分で回れます✨\n\n朝イチはアクアトピア→シーライダー→センターが狙い目🌅\n\n最高効率ルートはリプ欄👇\n\n※過去データに基づくシミュレーションです\n#東京ディズニーシー",
    "status": "posted",
    "posted_at": "2026-04-02T22:01:17.156762+00:00",
    "impressions": 0,
    "engagements": 0
  },
  {
    "date": "2026-04-02",
    "post_type": "daily_forecast",
    "content": "4/2東京ディズニーランド曇り予報☁️アトラク19個・待ち415分達成！朝イチはカリブ→ジャングル→ツリーハウスがおすすめ🏰最高効率ルートはリプ欄👇\n\n※過去データに基づくシミュレーションです\n#東京ディズニーランド #TDL",
    "status": "posted",
    "posted_at": "2026-04-02T22:00:43.223793+00:00",
    "impressions": 0,
    "engagements": 0
  },
  {
    "date": "2026-04-01",
    "post_type": "answer_check",
    "content": "📋4/1 東京ディズニーシー 振り返り\n\n実現率:100%(13/13個)\n予定609分→実際562分\n⬆️ゴンドラ:予27→実5\n✅アクアトピア:予5→実5\n\n※過去データに基づくシミュレーションです",
    "status": "posted",
    "posted_at": "2026-04-02T03:00:03.488844+00:00",
    "impressions": 0,
    "engagements": 0
  },
  {
    "date": "2026-04-01",
    "post_type": "answer_check",
    "content": "📋4/1 東京ディズニーランド 振り返り\n\n実現率:100%(19/19個)\n予定605分→実際592分\n⬆️カヌー:予26→実15\n✅チキルーム:予8→実8\n\n※過去データに基づくシミュレーションです",
    "status": "posted",
    "posted_at": "2026-04-02T03:00:02.387053+00:00",
    "impressions": 0,
    "engagements": 0
  },
  {
    "date": "2026-04-01",
    "post_type": "daily_forecast",
    "content": "【2026/4/1】東京ディズニーシー攻略プラン🎪\n曇り予想で13個アトラクション制覇可能！\n朝イチはアクアトピア→シーライダー→センターが正解🌊\n総待ち495分・移動59分で超効率回り✨\n最高効率ルートはリプ欄👇\n※過去データに基づくシミュレーションです\n#東京ディズニーシー #TDS",
    "status": "posted",
    "posted_at": "2026-04-01T22:01:08.024977+00:00",
    "impressions": 0,
    "engagements": 0
  },
  {
    "date": "2026-04-01",
    "post_type": "daily_forecast",
    "content": "2026/4/1(水)東京ディズニーランド攻略🏰\n曇り予想で19アトラクション制覇！総待ち411分✨\n朝イチおすすめ：カリブの海賊→ジャングルクルーズ→スイスファミリー🌲\n最高効率ルートはリプ欄👇\n#TDL #東京ディズニーランド\n※過去データに基づくシミュレーションです",
    "status": "posted",
    "posted_at": "2026-04-01T22:00:30.230998+00:00",
    "impressions": 0,
    "engagements": 0
  },
  {
    "date": "2026-04-01",
    "post_type": "monthly_calendar",
    "content": "📆 2026年4月 東京ディズニーシー 混雑予測\n\n第1週: 🟠Lv.3\n第2週: 🟠Lv.3\n第3週: 🟠Lv.3\n第4週: 🟠Lv.3\n第5週: 🟠Lv.3\n\n※過去データに基づくシミュレーションです",
    "status": "posted",
    "posted_at": "2026-03-31T11:00:57.554408+00:00",
    "impressions": 0,
    "engagements": 0
  },
  {
    "date": "2026-04-01",
    "post_type": "monthly_calendar",
    "content": "📆 2026年4月 東京ディズニーランド 混雑予測\n\n第1週: 🟡Lv.2\n第2週: 🟡Lv.2\n第3週: 🟡Lv.2\n第4週: 🟡Lv.2\n第5週: 🟡Lv.2\n\n※過去データに基づくシミュレーションです",
    "status": "posted",
    "posted_at": "2026-03-31T11:00:32.146575+00:00",
    "impressions": 0,
    "engagements": 0
  },
  {
    "date": "2026-03-31",
    "post_type": "answer_check",
    "content": "📋3/31 東京ディズニーシー 振り返り\n\n実現率:100%(13/13個)\n予定609分→実際578分\n⬆️フランダー:予42→実22\n✅アクアトピア:予5→実5\n\n※過去データに基づくシミュレーションです",
    "status": "posted",
    "posted_at": "2026-04-01T03:00:03.355647+00:00",
    "impressions": 0,
    "engagements": 0
  },
  {
    "date": "2026-03-31",
    "post_type": "answer_check",
    "content": "📋3/31 東京ディズニーランド 振り返り\n\n実現率:100%(19/19個)\n予定605分→実際576分\n⬆️ハニハン:予42→実21\n✅カヌー:予25→実25\n\n※過去データに基づくシミュレーションです",
    "status": "posted",
    "posted_at": "2026-04-01T03:00:02.216820+00:00",
    "impressions": 0,
    "engagements": 0
  },
  {
    "date": "2026-03-31",
    "post_type": "daily_forecast",
    "content": "東京ディズニーシーでアトラクション13個制覇🎭\n曇り予報で総待ち495分、移動59分の効率プラン！\n\n朝イチは「アクアトピア→シーライダー→センター」が鉄板ルート⛴️\n\n最高効率ルートはリプ欄👇\n\n#東京ディズニーシー\n\n※過去データに基づくシミュレーションです",
    "status": "posted",
    "posted_at": "2026-03-31T22:00:55.089481+00:00",
    "impressions": 0,
    "engagements": 0
  },
  {
    "date": "2026-03-31",
    "post_type": "daily_forecast",
    "content": "東京ディズニーランドで19個制覇攻略！🌥️曇り予想で待ち411分の高効率プラン✨朝イチはカリブの海賊→ジャングルクルーズ→スイスファミリーツリーハウスがおすすめ！最高効率ルートはリプ欄👇\n\n※過去データに基づくシミュレーションです\n\n#東京ディズニーランド #TDL攻略",
    "status": "posted",
    "posted_at": "2026-03-31T22:00:31.396728+00:00",
    "impressions": 0,
    "engagements": 0
  },
  {
    "date": "2026-03-30",
    "post_type": "answer_check",
    "content": "📋3/30 東京ディズニーシー 振り返り\n\n実現率:71%(10/14個)\n予定608分→実際707分\n⬆️海底2万マイル:予61→実96\n✅キャラバンカルーセル:予5→実5\n\n※過去データに基づくシミュレーションです",
    "status": "posted",
    "posted_at": "2026-03-31T03:00:03.335642+00:00",
    "impressions": 0,
    "engagements": 0
  },
  {
    "date": "2026-03-30",
    "post_type": "answer_check",
    "content": "📋3/30 東京ディズニーランド 振り返り\n\n実現率:74%(14/19個)\n予定604分→実際782分\n⬆️スプラッシュ:予96→実212\n✅ジャンクル:予7→実7\n\n※過去データに基づくシミュレーションです",
    "status": "posted",
    "posted_at": "2026-03-31T03:00:02.206791+00:00",
    "impressions": 0,
    "engagements": 0
  },
  {
    "date": "2026-03-30",
    "post_type": "daily_forecast",
    "content": "東京ディズニーシーで14個アトラクション制覇✨\n朝イチはアクアトピア→シーライダー→センターが正解！\n曇り予想で総待ち494分、効率よく回れます🎢\n\n最高効率ルートはリプ欄👇\n#東京ディズニーシー #TDS\n\n※過去データに基づくシミュレーションです",
    "status": "posted",
    "posted_at": "2026-03-30T22:03:30.112946+00:00",
    "impressions": 0,
    "engagements": 0
  },
  {
    "date": "2026-03-30",
    "post_type": "daily_forecast",
    "content": "【3/30】東京ディズニーランドで19個制覇🏃‍♂️\n曇り予想の朝イチはカリブ→ジャンクル→ツリーハウス🌲\n総待ち410分で効率よく周回✨\n\n最高効率ルートはリプ欄👇\n#TDL\n※過去データに基づくシミュレーションです",
    "status": "posted",
    "posted_at": "2026-03-30T22:01:53.604007+00:00",
    "impressions": 0,
    "engagements": 0
  },
  {
    "date": "2026-03-29",
    "post_type": "answer_check",
    "content": "📋3/29 東京ディズニーシー 振り返り\n\n実現率:88%(15/17個)\n予定582分→実際733分\n⬆️タートル・トーク:予25→実69\n✅キャラバンカルーセル:予5→実5\n\n※過去データに基づくシミュレーションです",
    "status": "posted",
    "posted_at": "2026-03-30T03:00:04.026960+00:00",
    "impressions": 0,
    "engagements": 0
  },
  {
    "date": "2026-03-29",
    "post_type": "answer_check",
    "content": "📋3/29 東京ディズニーランド 振り返り\n\n実現率:56%(5/9個)\n予定610分→実際723分\n⬆️ビッグサンダー:予63→実123\n✅ハニハン:予41→実42\n\n※過去データに基づくシミュレーションです",
    "status": "posted",
    "posted_at": "2026-03-30T03:00:02.788068+00:00",
    "impressions": 0,
    "engagements": 0
  },
  {
    "date": "2026-03-29",
    "post_type": "daily_forecast",
    "content": "3/29(日)東京ディズニーシー攻略📍\n曇り予報で17個アトラクション制覇可能！🎢\n朝イチはキャラバンカルーセル→シンド→ジェリーフィッシュがおすすめ✨\n総待ち362分で余裕の1日🌅\n\n最高効率ルートはリプ欄👇\n#東京ディズニーシー #TDS\n※過去データに基づくシミュレーションです",
    "status": "posted",
    "posted_at": "2026-03-29T22:01:12.273549+00:00",
    "impressions": 0,
    "engagements": 0
  },
  {
    "date": "2026-03-29",
    "post_type": "daily_forecast",
    "content": "3/29東京ディズニーランド攻略🏰\n\n曇り予報の日、9アトラクション攻略可能✨\n朝イチは美女と野獣→ベイマックス→モンインが鉄板ルート！\n\n最高効率ルートはリプ欘👇\n\n#東京ディズニーランド #TDL\n\n※過去データに基づくシミュレーションです",
    "status": "posted",
    "posted_at": "2026-03-29T22:00:35.596111+00:00",
    "impressions": 0,
    "engagements": 0
  },
  {
    "date": "2026-03-28",
    "post_type": "answer_check",
    "content": "📋3/28 東京ディズニーシー 振り返り\n\n実現率:94%(16/17個)\n予定579分→実際649分\n⬆️アクアトピア:予5→実35\n✅キャラバンカルーセル:予5→実5\n\n※過去データに基づくシミュレーションです",
    "status": "posted",
    "posted_at": "2026-03-29T03:00:03.395300+00:00",
    "impressions": 0,
    "engagements": 0
  },
  {
    "date": "2026-03-28",
    "post_type": "answer_check",
    "content": "📋3/28 東京ディズニーランド 振り返り\n\n実現率:84%(16/19個)\n予定607分→実際696分\n⬆️スプラッシュ:予100→実178\n✅チキルーム:予8→実8\n\n※過去データに基づくシミュレーションです",
    "status": "posted",
    "posted_at": "2026-03-29T03:00:02.155811+00:00",
    "impressions": 0,
    "engagements": 0
  },
  {
    "date": "2026-03-28",
    "post_type": "daily_forecast",
    "content": "【3/28東京ディズニーシー】曇りで17アトラクション制覇🎯総待ち372分！朝イチはキャラバンカルーセル→シンド→ジェリーフィッシュがおすすめ🏰最高効率ルートはリプ欄👇 #TDS ※過去データに基づくシミュレーションです",
    "status": "posted",
    "posted_at": "2026-03-28T22:01:14.574358+00:00",
    "impressions": 0,
    "engagements": 0
  },
  {
    "date": "2026-03-28",
    "post_type": "daily_forecast",
    "content": "🏰3/28(土)東京ディズニーランド攻略プラン\n\n曇り予想でアトラクション19個制覇可能！🎉\n朝イチは「カリブの海賊」からスタートでスムーズに🏴‍☠️\n総待ち時間408分の効率ルートを紹介します！\n\n最高効率ルートはリプ欄👇\n\n#東京ディズニーランド\n\n※過去データに基づくシミュレーションです",
    "status": "posted",
    "posted_at": "2026-03-28T22:00:31.012300+00:00",
    "impressions": 0,
    "engagements": 0
  },
  {
    "date": "2026-03-28",
    "post_type": "weekend_forecast",
    "content": "📅 今週末の東京ディズニーシー混雑予測\n\n🔵 土曜 3/28: Lv.3(やや混雑)\n🔵 日曜 3/29: Lv.3(やや混雑)\n\n天気: 曇り\nおすすめ: 土曜がやや空いてます\n\n※過去データに基づくシミュレーションです",
    "status": "posted",
    "posted_at": "2026-03-26T11:00:08.257175+00:00",
    "impressions": 0,
    "engagements": 0
  },
  {
    "date": "2026-03-28",
    "post_type": "weekend_forecast",
    "content": "📅 今週末の東京ディズニーランド混雑予測\n\n🔵 土曜 3/28: Lv.2(普通)\n🔵 日曜 3/29: Lv.2(普通)\n\n天気: 曇り\nおすすめ: 土曜がやや空いてます\n\n※過去データに基づくシミュレーションです",
    "status": "posted",
    "posted_at": "2026-03-26T11:00:05.269889+00:00",
    "impressions": 0,
    "engagements": 0
  },
  {
    "date": "2026-03-27",
    "post_type": "answer_check",
    "content": "📋3/27 東京ディズニーシー 振り返り\n\n実現率:82%(14/17個)\n予定593分→実際731分\n⬆️アクアトピア:予5→実50\n✅キャラバンカルーセル:予5→実5\n\n※過去データに基づくシミュレーションです",
    "status": "posted",
    "posted_at": "2026-03-28T03:00:04.008436+00:00",
    "impressions": 0,
    "engagements": 0
  },
  {
    "date": "2026-03-27",
    "post_type": "answer_check",
    "content": "📋3/27 東京ディズニーランド 振り返り\n\n実現率:78%(14/18個)\n予定600分→実際709分\n⬆️スプラッシュ:予100→実165\n✅カリブの海賊:予12→実12\n\n※過去データに基づくシミュレーションです",
    "status": "posted",
    "posted_at": "2026-03-28T03:00:02.625502+00:00",
    "impressions": 0,
    "engagements": 0
  },
  {
    "date": "2026-03-27",
    "post_type": "daily_forecast",
    "content": "3/27東京ディズニーシーでアトラクション17個攻略プラン🏯\n朝イチはシンド→キャラバン→ジェリーフィッシュが最効率✨\n総待ち時間わずか364分で達成！\n最高効率ルートはリプ欄👇\n\n#東京ディズニーシー #TDS\n※過去データに基づくシミュレーションです",
    "status": "posted",
    "posted_at": "2026-03-27T22:00:58.495072+00:00",
    "impressions": 0,
    "engagements": 0
  },
  {
    "date": "2026-03-27",
    "post_type": "daily_forecast",
    "content": "3/27東京ディズニーランド攻略！曇り予報で18アトラクション制覇可能🎪総待ち時間415分。朝イチはカリブの海賊→ジャングルクルーズ→スイスファミリーがおすすめ✨最高効率ルートはリプ欄👇 #TDL\n\n※過去データに基づくシミュレーションです",
    "status": "posted",
    "posted_at": "2026-03-27T22:00:30.944139+00:00",
    "impressions": 0,
    "engagements": 0
  },
  {
    "date": "2026-03-26",
    "post_type": "answer_check",
    "content": "📋3/26 東京ディズニーシー 振り返り\n\n実現率:100%(13/13個)\n予定601分→実際548分\n⬆️センター:予146→実96\n✅アクアトピア:予5→実5\n\n※過去データに基づくシミュレーションです",
    "status": "posted",
    "posted_at": "2026-03-27T03:00:03.411026+00:00",
    "impressions": 0,
    "engagements": 0
  },
  {
    "date": "2026-03-26",
    "post_type": "answer_check",
    "content": "📋3/26 東京ディズニーランド 振り返り\n\n実現率:95%(18/19個)\n予定609分→実際628分\n⬆️カヌー:予26→実5\n✅カリブの海賊:予11→実12\n\n※過去データに基づくシミュレーションです",
    "status": "posted",
    "posted_at": "2026-03-27T03:00:02.217762+00:00",
    "impressions": 0,
    "engagements": 0
  },
  {
    "date": "2026-03-26",
    "post_type": "daily_forecast",
    "content": "3/26曇りの東京ディズニーシーで13アトラクション攻略⭐総待ち492分✨朝イチはアクアトピア→シーライダー→センターへGO🌊最高効率ルートはリプ欄👇\n\n※過去データに基づくシミュレーションです\n\n#東京ディズニーシー #TDS",
    "status": "posted",
    "posted_at": "2026-03-26T22:01:05.309766+00:00",
    "impressions": 0,
    "engagements": 0
  },
  {
    "date": "2026-03-26",
    "post_type": "daily_forecast",
    "content": "2026/3/26（曇り）東京ディズニーランド攻略🏰\n\nなんとアトラクション19個制覇可能！総待ち時間415分で回れます✨\n\n朝イチはカリブの海賊→ジャングルクルーズ→スイスファミリーが鉄板ルート⛵\n\n最高効率ルートはリプ欄👇\n\n※過去データに基づくシミュレーションです\n\n#東京ディズニーランド #TDL",
    "status": "posted",
    "posted_at": "2026-03-26T22:00:34.841546+00:00",
    "impressions": 0,
    "engagements": 0
  },
  {
    "date": "2026-03-25",
    "post_type": "answer_check",
    "content": "📋3/25 東京ディズニーシー 振り返り\n\n実現率:70%(7/10個)\n予定610分→実際698分\n⬆️タワテラ:予130→実168\n✅キャラバンカルーセル:予6→実5\n\n※過去データに基づくシミュレーションです",
    "status": "posted",
    "posted_at": "2026-03-26T03:00:03.794190+00:00",
    "impressions": 0,
    "engagements": 0
  },
  {
    "date": "2026-03-25",
    "post_type": "answer_check",
    "content": "📋3/25 東京ディズニーランド 振り返り\n\n実現率:50%(6/12個)\n予定607分→実際756分\n⬆️ベイマックス:予62→実103\n✅モンイン:予84→実96\n\n※過去データに基づくシミュレーションです",
    "status": "posted",
    "posted_at": "2026-03-26T03:00:02.708302+00:00",
    "impressions": 0,
    "engagements": 0
  },
  {
    "date": "2026-03-25",
    "post_type": "daily_forecast",
    "content": "【2026/3/25】東京ディズニーシー雨予想☂️\n\n10個制覇、総待ち481分！\n\n朝イチはトイマニ→タワテラ→タートル・トークが最適🎯\n\n最高効率ルートはリプ欄👇\n\n※過去データに基づくシミュレーションです #TDS",
    "status": "posted",
    "posted_at": "2026-03-25T22:01:08.161102+00:00",
    "impressions": 0,
    "engagements": 0
  },
  {
    "date": "2026-03-25",
    "post_type": "daily_forecast",
    "content": "2026/3/25(水)東京ディズニーランド攻略プラン☔\n\n雨の日も12個アトラクション制覇！総待ち時間500分\n\n朝イチは美女と野獣→モンイン→ベイマックスの黄金ルート✨\n\n最高効率ルートはリプ欄👇\n\n#東京ディズニーランド #TDL\n\n※過去データに基づくシミュレーションです",
    "status": "posted",
    "posted_at": "2026-03-25T22:00:33.599279+00:00",
    "impressions": 0,
    "engagements": 0
  },
  {
    "date": "2026-03-24",
    "post_type": "answer_check",
    "content": "📋3/24 東京ディズニーシー 振り返り\n\n実現率:100%(13/13個)\n予定609分→実際604分\n⬆️ブローフィッシュ:予39→実33\n✅アクアトピア:予5→実5\n\n※過去データに基づくシミュレーションです",
    "status": "posted",
    "posted_at": "2026-03-25T03:00:03.097793+00:00",
    "impressions": 0,
    "engagements": 0
  },
  {
    "date": "2026-03-24",
    "post_type": "answer_check",
    "content": "📋3/24 東京ディズニーランド 振り返り\n\n実現率:84%(16/19個)\n予定605分→実際654分\n⬆️スプラッシュ:予93→実137\n✅カリブの海賊:予11→実11\n\n※過去データに基づくシミュレーションです",
    "status": "posted",
    "posted_at": "2026-03-25T03:00:01.929144+00:00",
    "impressions": 0,
    "engagements": 0
  },
  {
    "date": "2026-03-24",
    "post_type": "daily_forecast",
    "content": "3/24東京ディズニーシー1日プラン🌊\n曇り予想で13個制覇可能！✨\n朝イチはアクアトピア→シーライダー→センターがおすすめ🎬\n待ち時間495分、移動59分で効率バッチリ🎢\n\n最高効率ルートはリプ欘👇\n#東京ディズニーシー\n\n※過去データに基づくシミュレーションです",
    "status": "posted",
    "posted_at": "2026-03-24T22:01:03.301211+00:00",
    "impressions": 0,
    "engagements": 0
  },
  {
    "date": "2026-03-24",
    "post_type": "daily_forecast",
    "content": "3/24東京ディズニーランド、曇りで19個制覇可能！🎢\n朝イチはカリブの海賊→ジャングルクルーズ→スイスファミリーが正解ルート🐘\n総待ち411分でこの回数は優秀✨\n\n最高効率ルートはリプ欄👇\n\n※過去データに基づくシミュレーションです\n\n#東京ディズニーランド #TDL",
    "status": "posted",
    "posted_at": "2026-03-24T22:00:36.188214+00:00",
    "impressions": 0,
    "engagements": 0
  }
]